rda_python_icoads/PgIMMA.py
rda_python_icoads/R3.0-stat_doc.pdf
rda_python_icoads/README_R3.0_Subset.html
rda_python_icoads/__init__.py
rda_python_icoads/checkicoads.py
rda_python_icoads/cleanicoads.py
rda_python_icoads/countattm.py
rda_python_icoads/countattmvar.py
rda_python_icoads/counticoads.py
rda_python_icoads/countsst.py
rda_python_icoads/fillicoads.py
rda_python_icoads/fillinventory.py
rda_python_icoads/fillitable.py
rda_python_icoads/fillmonth.py
rda_python_icoads/fixiidx.py
rda_python_icoads/imma1_subset.py
rda_python_icoads/maxsst.py
rda_python_icoads/msg
rda_python_icoads/msg3.0_subset_readme.txt
rda_python_icoads/msg3_subset.py
rda_python_icoads/msg_download.py
rda_python_icoads/msgsubset.f
rda_python_icoads/rdimma1_csv.f
rda_python_icoads/writeicoads.py
rda_python_icoads-1.0.18.dist-info/licenses/LICENSE
rda_python_icoads-1.0.18.dist-info/METADATA
rda_python_icoads-1.0.18.dist-info/WHEEL
rda_python_icoads-1.0.18.dist-info/entry_points.txt
rda_python_icoads-1.0.18.dist-info/top_level.txt
rda_python_icoads-1.0.18.dist-info/RECORD
