Metadata-Version: 2.4
Name: rda_python_icoads
Version: 1.0.18
Summary: RDA python package to manage RDA ICOADS datasets
Author-email: Zaihua Ji <zji@ucar.edu>
Project-URL: Homepage, https://github.com/NCAR/rda-python-icoads
Classifier: Programming Language :: Python :: 3
Classifier: License :: OSI Approved :: MIT License
Classifier: Operating System :: OS Independent
Classifier: Development Status :: 5 - Production/Stable
Requires-Python: >=3.7
License-File: LICENSE
Requires-Dist: rda_python_common
Dynamic: license-file
